{
  "_schema_version": "1.0",
  "_meter": "earth_energy",
  "_last_updated": "Generated by Gemini",
  "metadata": {
    "meter_id": "earth_energy",
    "display_name": "Earth Energy",
    "group": "elements",
    "super_group": "deeper_dimensions",
    "group_description": "Temperament balance, elemental energy distribution",
    "super_group_description": "Foundational energies, spiritual awareness, and collective currents",
    "measures": "both"
  },
  "description": {
    "overview": "This meter shows how much practical, grounded energy is active in your day to get things done.",
    "detailed": "It measures planetary activity in earth signs like Taurus, Virgo, and Capricorn. This highlights your focus on the material world, structure, and getting things done. It influences your ability to manifest ideas into reality.",
    "keywords": [
      "grounding",
      "practical",
      "stability",
      "resources",
      "production"
    ]
  },
  "experience_labels": {
    "intensity_only": {
      "quiet": "Earth Still",
      "mild": "Gentle Ground",
      "moderate": "Steady Focus",
      "high": "Strong Build",
      "extreme": "Solid Impact"
    },
    "harmony_only": {
      "challenging": "Rough Terrain",
      "mixed": "Shifting Ground",
      "harmonious": "Firm Footing"
    },
    "combined": {
      "quiet": {
        "challenging": "Quiet Struggle",
        "mixed": "Gentle Shift",
        "harmonious": "Calm Foundation"
      },
      "mild": {
        "challenging": "Mild Friction",
        "mixed": "Gentle Adjust",
        "harmonious": "Easy Flow"
      },
      "moderate": {
        "challenging": "Key Obstacles",
        "mixed": "Stable Mix",
        "harmonious": "Productive Flow"
      },
      "high": {
        "challenging": "Major Blocks",
        "mixed": "Strong Push",
        "harmonious": "Peak Output"
      },
      "extreme": {
        "challenging": "Hard Confront",
        "mixed": "Big Shifts",
        "harmonious": "Solid Gains"
      }
    }
  },
  "advice_templates": {
    "quiet": {
      "challenging": "Reassess basics",
      "mixed": "Gentle planning",
      "harmonious": "Cultivate stillness"
    },
    "mild": {
      "challenging": "Minor adjustments",
      "mixed": "Flexible approach",
      "harmonious": "Steady maintenance"
    },
    "moderate": {
      "challenging": "Problem solving",
      "mixed": "Practical action",
      "harmonious": "Focused work"
    },
    "high": {
      "challenging": "Overcome hurdles",
      "mixed": "Strategic persistence",
      "harmonious": "Materialize goals"
    },
    "extreme": {
      "challenging": "Direct repair",
      "mixed": "Adapt to change",
      "harmonious": "Maximize results"
    }
  }
}