{
  "_schema_version": "1.0",
  "_meter": "decision_quality",
  "_last_updated": "Generated by Gemini",
  "metadata": {
    "meter_id": "decision_quality",
    "display_name": "Decision Quality",
    "group": "mind",
    "super_group": "inner_world",
    "group_description": "Cognitive function, communication, decision-making",
    "super_group_description": "Internal states\u2014thoughts, feelings, and inner resources",
    "measures": "both"
  },
  "description": {
    "overview": "This meter shows the quality of your judgment and how well you can make decisions right now.",
    "detailed": "This meter analyzes aspects involving Mercury, the Sun, and Jupiter to reveal your mental clarity and decision-making capacity. Saturn's influence adds a layer of caution, while Neptune can introduce confusion or uncertainty into your thought processes.",
    "keywords": [
      "Judgment",
      "Clarity",
      "Choices",
      "Insight",
      "Discernment"
    ]
  },
  "experience_labels": {
    "intensity_only": {
      "quiet": "Calm Thoughts",
      "mild": "Gentle Focus",
      "moderate": "Clear Thinking",
      "high": "Sharp Insight",
      "extreme": "Intense Focus"
    },
    "harmony_only": {
      "challenging": "Tough Calls",
      "mixed": "Nuanced Views",
      "harmonious": "Good Judgment"
    },
    "combined": {
      "quiet": {
        "challenging": "Hazy Thoughts",
        "mixed": "Passive Mixed",
        "harmonious": "Calm Clarity"
      },
      "mild": {
        "challenging": "Slight Friction",
        "mixed": "Gentle Mixed",
        "harmonious": "Easy Flow"
      },
      "moderate": {
        "challenging": "Tricky Choices",
        "mixed": "Focused Mixed",
        "harmonious": "Clear Purpose"
      },
      "high": {
        "challenging": "Demanding Calls",
        "mixed": "Strong Nuance",
        "harmonious": "Sharp Insight"
      },
      "extreme": {
        "challenging": "Intense Pressure",
        "mixed": "Urgent Mix",
        "harmonious": "Peak Wisdom"
      }
    }
  },
  "advice_templates": {
    "quiet": {
      "challenging": "Wait & Reflect",
      "mixed": "Observe & Ponder",
      "harmonious": "Trust Intuition"
    },
    "mild": {
      "challenging": "Gentle Approach",
      "mixed": "Consider Options",
      "harmonious": "Go WithFlow"
    },
    "moderate": {
      "challenging": "Strategic Planning",
      "mixed": "Weigh ProsCons",
      "harmonious": "Confident Decisions"
    },
    "high": {
      "challenging": "Careful Strategy",
      "mixed": "Adapt & Adjust",
      "harmonious": "Decisive Action"
    },
    "extreme": {
      "challenging": "Crisis Management",
      "mixed": "Urgent Assessment",
      "harmonious": "Bold Breakthrough"
    }
  }
}